Workbook

Sheet Resumo
B2: KIXIMA — Product Backlog
B3: Um único backlog, organizado por Sprint
B5: Total de itens | C5: =COUNTA(Backlog!A2:A71)
B6: Concluído | C6: =COUNTIF(Backlog!D2:D71,"Concluído") | D6: =C6/$C$5
B7: Em Curso | C7: =COUNTIF(Backlog!D2:D71,"Em Curso") | D7: =C7/$C$5
B8: Pendente | C8: =COUNTIF(Backlog!D2:D71,"Pendente") | D8: =C8/$C$5
B10: Pendentes por prioridade
B11: Alta | C11: =COUNTIFS(Backlog!D2:D71,"Pendente",Backlog!E2:E71,"Alta")
B12: Média | C12: =COUNTIFS(Backlog!D2:D71,"Pendente",Backlog!E2:E71,"Média")
B13: Baixa | C13: =COUNTIFS(Backlog!D2:D71,"Pendente",Backlog!E2:E71,"Baixa")
B15: Progresso por Sprint
B16: Sprint | C16: Concluído | D16: Em Curso | E16: Pendente | F16: Total | G16: % Progresso
B17: Sprint 1 — Núcleo do Marketplace | C17: =COUNTIFS(Backlog!$B$2:$B$71,$B17,Backlog!$D$2:$D$71,"Concluído") | D17: =COUNTIFS(Backlog!$B$2:$B$71,$B17,Backlog!$D$2:$D$71,"Em Curso") | E17: =COUNTIFS(Backlog!$B$2:$B$71,$B17,Backlog!$D$2:$D$71,"Pendente") | F17: =C17+D17+E17 | G17: =C17/F17
B18: Sprint 2 — Segurança & Controlo de Acesso | C18: =COUNTIFS(Backlog!$B$2:$B$71,$B18,Backlog!$D$2:$D$71,"Concluído") | D18: =COUNTIFS(Backlog!$B$2:$B$71,$B18,Backlog!$D$2:$D$71,"Em Curso") | E18: =COUNTIFS(Backlog!$B$2:$B$71,$B18,Backlog!$D$2:$D$71,"Pendente") | F18: =C18+D18+E18 | G18: =C18/F18
B19: Sprint 3 — Suporte & Confiança | C19: =COUNTIFS(Backlog!$B$2:$B$71,$B19,Backlog!$D$2:$D$71,"Concluído") | D19: =COUNTIFS(Backlog!$B$2:$B$71,$B19,Backlog!$D$2:$D$71,"Em Curso") | E19: =COUNTIFS(Backlog!$B$2:$B$71,$B19,Backlog!$D$2:$D$71,"Pendente") | F19: =C19+D19+E19 | G19: =C19/F19
B20: Sprint 4 — Ordens de Compra | C20: =COUNTIFS(Backlog!$B$2:$B$71,$B20,Backlog!$D$2:$D$71,"Concluído") | D20: =COUNTIFS(Backlog!$B$2:$B$71,$B20,Backlog!$D$2:$D$71,"Em Curso") | E20: =COUNTIFS(Backlog!$B$2:$B$71,$B20,Backlog!$D$2:$D$71,"Pendente") | F20: =C20+D20+E20 | G20: =C20/F20
B21: Sprint 5 — Subscrições & Pagamentos | C21: =COUNTIFS(Backlog!$B$2:$B$71,$B21,Backlog!$D$2:$D$71,"Concluído") | D21: =COUNTIFS(Backlog!$B$2:$B$71,$B21,Backlog!$D$2:$D$71,"Em Curso") | E21: =COUNTIFS(Backlog!$B$2:$B$71,$B21,Backlog!$D$2:$D$71,"Pendente") | F21: =C21+D21+E21 | G21: =C21/F21
B22: Sprint 6 — Faturação & Fiscalidade (AGT) | C22: =COUNTIFS(Backlog!$B$2:$B$71,$B22,Backlog!$D$2:$D$71,"Concluído") | D22: =COUNTIFS(Backlog!$B$2:$B$71,$B22,Backlog!$D$2:$D$71,"Em Curso") | E22: =COUNTIFS(Backlog!$B$2:$B$71,$B22,Backlog!$D$2:$D$71,"Pendente") | F22: =C22+D22+E22 | G22: =C22/F22
B23: Sprint 7 — Página Institucional & Marketing | C23: =COUNTIFS(Backlog!$B$2:$B$71,$B23,Backlog!$D$2:$D$71,"Concluído") | D23: =COUNTIFS(Backlog!$B$2:$B$71,$B23,Backlog!$D$2:$D$71,"Em Curso") | E23: =COUNTIFS(Backlog!$B$2:$B$71,$B23,Backlog!$D$2:$D$71,"Pendente") | F23: =C23+D23+E23 | G23: =C23/F23
B24: Sprint 8 — Documentação | C24: =COUNTIFS(Backlog!$B$2:$B$71,$B24,Backlog!$D$2:$D$71,"Concluído") | D24: =COUNTIFS(Backlog!$B$2:$B$71,$B24,Backlog!$D$2:$D$71,"Em Curso") | E24: =COUNTIFS(Backlog!$B$2:$B$71,$B24,Backlog!$D$2:$D$71,"Pendente") | F24: =C24+D24+E24 | G24: =C24/F24
B25: Sprint 9 — Ambiente de Teste & Lançamento | C25: =COUNTIFS(Backlog!$B$2:$B$71,$B25,Backlog!$D$2:$D$71,"Concluído") | D25: =COUNTIFS(Backlog!$B$2:$B$71,$B25,Backlog!$D$2:$D$71,"Em Curso") | E25: =COUNTIFS(Backlog!$B$2:$B$71,$B25,Backlog!$D$2:$D$71,"Pendente") | F25: =C25+D25+E25 | G25: =C25/F25
B26: TOTAL | C26: =SUM(C17:C25) | D26: =SUM(D17:D25) | E26: =SUM(E17:E25) | F26: =SUM(F17:F25) | G26: =C26/F26

Sheet Backlog
A1: Nº | B1: Sprint | C1: Item do Backlog | D1: Estado | E1: Prioridade | F1: Notas
A2: 1 | B2: Sprint 1 — Núcleo do Marketplace | C2: Catálogo de produtos e serviços (fornecedor publica, comprador explora e compara) | D2: Concluído | E2: — | F2: Inclui kits, importação em massa via Excel (plano PRO) e API de sincronização de preço/stock.
A3: 2 | B3: Sprint 1 — Núcleo do Marketplace | C3: Cotações (RFQ) entre comprador e fornecedor | D3: Concluído | E3: — | F3: Pedido → resposta com preço/prazo → fecho pelo comprador.
A4: 3 | B4: Sprint 1 — Núcleo do Marketplace | C4: Ciclo completo de Ordens de Compra | D4: Concluído | E4: — | F4: Aprovação, aceitação, pagamento, execução, entrega, receção e resolução de divergências — 11 estados.
A5: 4 | B5: Sprint 1 — Núcleo do Marketplace | C5: Contratos-quadro e encomendas avulsas (call-offs) | D5: Concluído | E5: — | F5: Deteção automática no checkout + faturação consolidada periódica (plano PRO).
A6: 5 | B6: Sprint 1 — Núcleo do Marketplace | C6: Cadastro e aprovação de empresas (due diligence documental) | D6: Concluído | E6: — | F6: Documentos por tipo de empresa (Cliente/Fornecedora) + apólice obrigatória para fornecedores.
A7: 6 | B7: Sprint 1 — Núcleo do Marketplace | C7: Gestão de utilizadores, convites e perfis por empresa | D7: Concluído | E7: — | F7: Perfis: Comprador, Company Admin, Fornecedor, Financeiro.
A8: 7 | B8: Sprint 1 — Núcleo do Marketplace | C8: Painel do Admin do Sistema (empresas, apólices, contratos, taxas, planos) | D8: Concluído | E8: — | F8: —
A9: 8 | B9: Sprint 1 — Núcleo do Marketplace | C9: Auditoria (trilho append-only de todas as ações) | D9: Concluído | E9: — | F9: Nunca editável/apagável; ator desnormalizado sobrevive à remoção da conta.
A10: 9 | B10: Sprint 1 — Núcleo do Marketplace | C10: Apólices de seguro (Fornecedor→KIXIMA e KIXIMA→Cliente) | D10: Concluído | E10: — | F10: Condição de credenciamento para fornecedores.
A11: 10 | B11: Sprint 2 — Segurança & Controlo de Acesso | C11: Autenticação de dois fatores (2FA) — email ou aplicação (TOTP) | D11: Concluído | E11: — | F11: Obrigatória para Company Admin e Admin do Sistema.
A12: 11 | B12: Sprint 2 — Segurança & Controlo de Acesso | C12: Bloqueio progressivo de conta por tentativas falhadas de login | D12: Concluído | E12: — | F12: Por conta, nunca por IP — protege escritórios inteiros atrás do mesmo endereço.
A13: 12 | B13: Sprint 2 — Segurança & Controlo de Acesso | C13: Admin do Sistema dividido por 6 áreas de permissão + Super Admin | D13: Concluído | E13: — | F13: Cadastro, Financeiro, Faturação (AGT), Apólices, Suporte, Operação da Plataforma.
... A71: 70 | B71: Sprint 9 — Ambiente de Teste & Lançamento | C71: Rastreio de erros em produção (Sentry) | D71: Pendente | E71: Baixa | F71: Opcional, recomendado antes de abrir a operadoras.
